MANIFEST.in
README
setup.py
django_shop_stripe.egg-info/PKG-INFO
django_shop_stripe.egg-info/SOURCES.txt
django_shop_stripe.egg-info/dependency_links.txt
django_shop_stripe.egg-info/top_level.txt
django_shop_stripe.egg-info/zip-safe
shop_stripe/__init__.py
shop_stripe/forms.py
shop_stripe/models.py
shop_stripe/offsite_stripe.py
shop_stripe/views.py