Metadata-Version: 1.0
Name: django-shop-stripe
Version: 0.1.0
Summary: Let us use stripe for payments with django-shop.
Home-page: http://github.com/powellc/django-shop-stripe
Author: Colin Powell
Author-email: colin@onecardinal.com
License: BSD
Download-URL: http://github.com/powellc/django-shop-stripe/downloads
Platform: UNKNOWN
Classifier: Development Status :: 4 - Beta
Classifier: Environment :: Web Environment
Classifier: Intended Audience :: Developers
Classifier: License :: OSI Approved :: BSD License
Classifier: Operating System :: OS Independent
Classifier: Programming Language :: Python
Classifier: Framework :: Django
